pypyr_scheduler_cli-1.0.3-py3.8-nspkg.pth
pyrsched/cli/__init__.py
pyrsched/cli/__main__.py
pypyr_scheduler_cli-1.0.3.dist-info/LICENSE
pypyr_scheduler_cli-1.0.3.dist-info/METADATA
pypyr_scheduler_cli-1.0.3.dist-info/WHEEL
pypyr_scheduler_cli-1.0.3.dist-info/namespace_packages.txt
pypyr_scheduler_cli-1.0.3.dist-info/top_level.txt
pypyr_scheduler_cli-1.0.3.dist-info/RECORD
